readtime_cli/__init__.py
readtime_cli/main.py
readtime_cli/translate.py
readtime_cli-0.2.3.dist-info/METADATA
readtime_cli-0.2.3.dist-info/entry_points.txt
readtime_cli-0.2.3.dist-info/WHEEL
readtime_cli-0.2.3.dist-info/RECORD
