Metadata-Version: 2.1
Name: readtime-cli
Version: 0.2.3
Summary: CLI to calculates the time some text takes the average human to read, based on Medium's read time forumula.
Home-page: https://github.com/guedesfelipe/readtime_cli
Keywords: python,readtime,readtime_cli,cli
Author: Felipe Guedes
Author-email: contatofelipeguedes@gmail.com
Requires-Python: >=3.8,<3.11
Classifier: Programming Language :: Python :: 3
Classifier: Programming Language :: Python :: 3.8
Classifier: Programming Language :: Python :: 3.9
Classifier: Programming Language :: Python :: 3.10
Requires-Dist: lxml (==4.9.0)
Requires-Dist: readtime (>=2.0.0,<3.0.0)
Requires-Dist: typer[all] (>=0.6.1,<0.8.0)
Project-URL: Documentation, https://github.com/guedesfelipe/readtime_cli
Project-URL: Repository, https://github.com/guedesfelipe/readtime_cli
